Metadata-Version: 2.4
Name: venai-foobartest
Version: 1.28.4
Summary: VenusAI is a secure and extensible Agent framework built for modern AI applications.
Home-page: https://github.com/VenusAgent/VenusAI
Author: Mert Sirakaya
Author-email: contact@tomris.dev
Maintainer: Mert Sirakaya
Maintainer-email: contact@tomris.dev
License: MIT
Project-URL: Documentation, https://venai.tech/docs
Project-URL: Source, https://github.com/VenusAgent/VenusAI
Project-URL: Tracker, https://github.com/VenusAgent/VenusAI/issues
Keywords: safety,ai,agent,llm,agentic ai,pydantic,pydantic-ai,self-healing,sandbox,ai agent
Classifier: Programming Language :: Python :: 3.10
Classifier: Programming Language :: Python :: 3.11
Classifier: Programming Language :: Python :: 3.12
Classifier: License :: OSI Approved :: MIT License
Classifier: Operating System :: OS Independent
Requires-Python: >=3.10
License-File: LICENSE
Requires-Dist: mcp
Requires-Dist: rich
Requires-Dist: click
Requires-Dist: tinydb
Requires-Dist: fasta2a
Requires-Dist: attrobj
Requires-Dist: fastapi
Requires-Dist: logfire
Requires-Dist: uvicorn
Requires-Dist: pydantic
Requires-Dist: aiocache
Requires-Dist: aiofiles
Requires-Dist: async-lru
Requires-Dist: cachetools
Requires-Dist: pydantic-ai
Requires-Dist: python-dotenv
Requires-Dist: typing-extensions
Requires-Dist: e2b-code-interpreter
Dynamic: author
Dynamic: author-email
Dynamic: classifier
Dynamic: description
Dynamic: description-content-type
Dynamic: home-page
Dynamic: keywords
Dynamic: license
Dynamic: license-file
Dynamic: maintainer
Dynamic: maintainer-email
Dynamic: project-url
Dynamic: requires-dist
Dynamic: requires-python
Dynamic: summary
